setup.py
pyvst/__init__.py
pyvst/aeffect.py
pyvst/vstplugin.py
pyvst.egg-info/PKG-INFO
pyvst.egg-info/SOURCES.txt
pyvst.egg-info/dependency_links.txt
pyvst.egg-info/top_level.txt